lightning_rest/__init__.py
lightning_rest/lightning.py
lightning_rest/server.py
lightning_rest-0.2.1.dist-info/DESCRIPTION.rst
lightning_rest-0.2.1.dist-info/METADATA
lightning_rest-0.2.1.dist-info/RECORD
lightning_rest-0.2.1.dist-info/WHEEL
lightning_rest-0.2.1.dist-info/metadata.json
lightning_rest-0.2.1.dist-info/top_level.txt
