Metadata-Version: 2.0
Name: lightning-rest
Version: 0.2.1
Summary: Rest server for the `lightningd` RPC.
Home-page: https://github.com/hbasria/lightning-rest
Author: Hasan Basri
Author-email: hbasria@gmail.com
License: MIT
Keywords: lightning rest api
Platform: UNKNOWN
Classifier: Development Status :: 4 - Beta
Classifier: Intended Audience :: Developers
Classifier: License :: OSI Approved :: MIT License
Classifier: Programming Language :: Python
Classifier: Programming Language :: Python :: 2
Classifier: Programming Language :: Python :: 2.7
Classifier: Programming Language :: Python :: 3
Classifier: Programming Language :: Python :: 3.3
Classifier: Programming Language :: Python :: 3.4
Classifier: Topic :: Software Development
Classifier: Topic :: Software Development :: Libraries :: Python Modules
Requires-Dist: aiohttp-swagger (<=2.0,>=1.0.5)
